<?xml version="1.0" encoding="utf-8" ?>
<dwsync>
<file name="temp-featured.php" server="ftp.prosentra.com//" local="131690969369817007" remote="131691119400000000" Dst="0" />
<file name="temp-category-posts.php" server="ftp.prosentra.com//" local="131690763881319513" remote="131690908800000000" Dst="0" />
<file name="temp-comments.php" server="ftp.prosentra.com//" local="131683910700000000" remote="131684420400000000" Dst="0" />
<file name="temp-download.php" server="ftp.prosentra.com//" local="131699823171876690" remote="131699535000000000" Dst="0" />
<file name="temp-newsletter.php" server="ftp.prosentra.com//" local="131683910700000000" remote="131684420400000000" Dst="0" />
<file name="temp-popular.php" server="ftp.prosentra.com//" local="131699825185005933" remote="131699538600000000" Dst="0" />
<file name="temp-recent-posts.php" server="ftp.prosentra.com//" local="131699825780982884" remote="131699538600000000" Dst="0" />
<file name="temp-slider-nav.php" server="ftp.prosentra.com//" local="131683910700000000" remote="131684420400000000" Dst="0" />
<file name="temp-top-header.php" server="ftp.prosentra.com//" local="131698027216972818" remote="131697803400000000" Dst="0" />
<file name="temp-video.php" server="ftp.prosentra.com//" local="131683910700000000" remote="131684420400000000" Dst="0" />
<file name="temp-blog-post.php" server="ftp.prosentra.com//" local="131699822183594512" remote="131699534400000000" Dst="0" />
</dwsync>